{"version": "4.1.1", "flags": {}, "shapes": [{"label": "mtp_5", "points": [[437.3968253968253, 618.047619047619]], "group_id": null, "shape_type": "point", "flags": {}}, {"label": "mtp_4", "points": [[550.0952380952381, 549.7936507936508]], "group_id": null, "shape_type": "point", "flags": {}}, {"label": "mtp_3", "points": [[656.4444444444443, 508.5238095238095]], "group_id": null, "shape_type": "point", "flags": {}}, {"label": "mtp_2", "points": [[756.4444444444443, 506.93650793650795]], "group_id": null, "shape_type": "point", "flags": {}}, {"label": "mtp_1", "points": [[902.4761904761904, 589.4761904761905]], "group_id": null, "shape_type": "point", "flags": {}}, {"label": "mtp", "points": [[948.5079365079364, 391.06349206349205]], "group_id": null, "shape_type": "point", "flags": {}}], "imagePath": "..\\UAB150-LF.jpg", "imageData": "", "imageHeight": 1544, "imageWidth": 1160}