{"version": "4.1.1", "flags": {}, "shapes": [{"label": "mtp_5", "points": [[204.05555555555554, 501.5555555555556]], "group_id": null, "shape_type": "point", "flags": {}}, {"label": "mtp_4", "points": [[309.6111111111112, 448.77777777777777]], "group_id": null, "shape_type": "point", "flags": {}}, {"label": "mtp_3", "points": [[395.7222222222222, 394.61111111111114]], "group_id": null, "shape_type": "point", "flags": {}}, {"label": "mtp_2", "points": [[480.44444444444457, 369.61111111111114]], "group_id": null, "shape_type": "point", "flags": {}}, {"label": "mtp_1", "points": [[640.1666666666667, 400.1666666666667]], "group_id": null, "shape_type": "point", "flags": {}}, {"label": "mtp", "points": [[642.9444444444446, 272.3888888888889]], "group_id": null, "shape_type": "point", "flags": {}}], "imagePath": "..\\UAB145-LF.jpg", "imageData": "", "imageHeight": 1344, "imageWidth": 841}