{"version": "4.1.1", "flags": {}, "shapes": [{"label": "mtp_5", "points": [[116.86956521739131, 265.8478260869565]], "group_id": null, "shape_type": "point", "flags": {}}, {"label": "mtp_4", "points": [[158.7173913043478, 221.82608695652172]], "group_id": null, "shape_type": "point", "flags": {}}, {"label": "mtp_3", "points": [[200.56521739130432, 191.39130434782606]], "group_id": null, "shape_type": "point", "flags": {}}, {"label": "mtp_2", "points": [[237.52173913043475, 168.56521739130434]], "group_id": null, "shape_type": "point", "flags": {}}, {"label": "mtp_1", "points": [[323.391304347826, 174.0]], "group_id": null, "shape_type": "point", "flags": {}}, {"label": "mtp", "points": [[280.45652173913044, 72.91304347826086]], "group_id": null, "shape_type": "point", "flags": {}}], "imagePath": "..\\UAB422-LF.jpg", "imageData": "", "imageHeight": 527, "imageWidth": 479}