{"version": "4.2.4", "flags": {}, "shapes": [{"label": "0_mcp_ip", "points": [[875.7704918032787, 803.0983606557377]], "group_id": null, "shape_type": "point", "flags": {}}, {"label": "1_pip_2", "points": [[699.5409836065573, 417.8524590163934]], "group_id": null, "shape_type": "point", "flags": {}}, {"label": "2_pip_3", "points": [[488.06557377049194, 384.24590163934425]], "group_id": null, "shape_type": "point", "flags": {}}, {"label": "3_pip_4", "points": [[345.44262295081967, 407.1967213114754]], "group_id": null, "shape_type": "point", "flags": {}}, {"label": "4_pip_5", "points": [[165.11475409836066, 567.8524590163935]], "group_id": null, "shape_type": "point", "flags": {}}, {"label": "5_mcp_1", "points": [[776.5901639344263, 974.4098360655738]], "group_id": null, "shape_type": "point", "flags": {}}, {"label": "6_mcp_2", "points": [[657.7377049180329, 711.2950819672132]], "group_id": null, "shape_type": "point", "flags": {}}, {"label": "7_mcp_3", "points": [[502.0, 676.0491803278688]], "group_id": null, "shape_type": "point", "flags": {}}, {"label": "8_mcp_4", "points": [[370.03278688524597, 699.0]], "group_id": null, "shape_type": "point", "flags": {}}, {"label": "9_mcp_5", "points": [[220.03278688524597, 780.9672131147541]], "group_id": null, "shape_type": "point", "flags": {}}, {"label": "w1", "points": [[586.4262295081967, 1170.311475409836]], "group_id": null, "shape_type": "point", "flags": {}}, {"label": "w2", "points": [[399.54098360655735, 1258.016393442623]], "group_id": null, "shape_type": "point", "flags": {}}, {"label": "w3", "points": [[264.29508196721304, 1118.672131147541]], "group_id": null, "shape_type": "point", "flags": {}}], "imagePath": "UAB572-LH.jpg", "imageData": "", "imageHeight": 1668, "imageWidth": 1044}