{"version": "4.2.4", "flags": {}, "shapes": [{"label": "w3", "points": [[708.4000000000001, 1184.0]], "group_id": null, "shape_type": "point", "flags": {}}, {"label": "w2", "points": [[572.4000000000001, 1284.8]], "group_id": null, "shape_type": "point", "flags": {}}, {"label": "w1", "points": [[393.20000000000005, 1140.0]], "group_id": null, "shape_type": "point", "flags": {}}, {"label": "9_mcp_5", "points": [[830.0, 809.6]], "group_id": null, "shape_type": "point", "flags": {}}, {"label": "8_mcp_4", "points": [[717.2, 729.6]], "group_id": null, "shape_type": "point", "flags": {}}, {"label": "7_mcp_3", "points": [[610.0, 636.8]], "group_id": null, "shape_type": "point", "flags": {}}, {"label": "6_mcp_2", "points": [[438.0, 632.0]], "group_id": null, "shape_type": "point", "flags": {}}, {"label": "5_mcp_1", "points": [[231.60000000000002, 861.6]], "group_id": null, "shape_type": "point", "flags": {}}, {"label": "4_pip_5", "points": [[930.8, 611.2]], "group_id": null, "shape_type": "point", "flags": {}}, {"label": "3_pip_4", "points": [[774.0, 451.2]], "group_id": null, "shape_type": "point", "flags": {}}, {"label": "2_pip_3", "points": [[606.0, 342.4]], "group_id": null, "shape_type": "point", "flags": {}}, {"label": "1_pip_2", "points": [[406.79999999999995, 382.4]], "group_id": null, "shape_type": "point", "flags": {}}, {"label": "0_mcp_ip", "points": [[178.0, 674.4]], "group_id": null, "shape_type": "point", "flags": {}}], "imagePath": "UAB651-RH.jpg", "imageData": "", "imageHeight": 1621, "imageWidth": 1053}