{"version": "4.2.4", "flags": {}, "shapes": [{"label": "0_mcp_ip", "points": [[1036.875, 711.28125]], "group_id": null, "shape_type": "point", "flags": {}}, {"label": "1_pip_2", "points": [[779.0625, 446.4375]], "group_id": null, "shape_type": "point", "flags": {}}, {"label": "2_pip_3", "points": [[608.75, 410.5]], "group_id": null, "shape_type": "point", "flags": {}}, {"label": "3_pip_4", "points": [[422.8125, 504.25]], "group_id": null, "shape_type": "point", "flags": {}}, {"label": "4_pip_5", "points": [[308.75, 654.25]], "group_id": null, "shape_type": "point", "flags": {}}, {"label": "5_mcp_1", "points": [[979.84375, 932.375]], "group_id": null, "shape_type": "point", "flags": {}}, {"label": "6_mcp_2", "points": [[781.40625, 700.34375]], "group_id": null, "shape_type": "point", "flags": {}}, {"label": "7_mcp_3", "points": [[627.5, 714.40625]], "group_id": null, "shape_type": "point", "flags": {}}, {"label": "8_mcp_4", "points": [[500.9375, 781.59375]], "group_id": null, "shape_type": "point", "flags": {}}, {"label": "9_mcp_5", "points": [[397.03125, 866.75]], "group_id": null, "shape_type": "point", "flags": {}}, {"label": "w1", "points": [[846.25, 1168.3125]], "group_id": null, "shape_type": "point", "flags": {}}, {"label": "w2", "points": [[686.09375, 1273.0]], "group_id": null, "shape_type": "point", "flags": {}}, {"label": "w3", "points": [[515.0, 1167.53125]], "group_id": null, "shape_type": "point", "flags": {}}], "imagePath": "UAB700-LH.jpg", "imageData": "", "imageHeight": 1587, "imageWidth": 1196}