{"version": "4.2.4", "flags": {}, "shapes": [{"label": "w3", "points": [[507.13043478260875, 1679.5217391304348]], "group_id": null, "shape_type": "point", "flags": {}}, {"label": "w2", "points": [[726.695652173913, 1921.9130434782608]], "group_id": null, "shape_type": "point", "flags": {}}, {"label": "w1", "points": [[1003.8695652173913, 1783.8695652173913]], "group_id": null, "shape_type": "point", "flags": {}}, {"label": "9_mcp_5", "points": [[420.17391304347825, 1177.3478260869565]], "group_id": null, "shape_type": "point", "flags": {}}, {"label": "8_mcp_4", "points": [[640.8260869565217, 1078.4347826086955]], "group_id": null, "shape_type": "point", "flags": {}}, {"label": "7_mcp_3", "points": [[835.391304347826, 1018.6521739130434]], "group_id": null, "shape_type": "point", "flags": {}}, {"label": "6_mcp_2", "points": [[1089.7391304347825, 1054.5217391304348]], "group_id": null, "shape_type": "point", "flags": {}}, {"label": "5_mcp_1", "points": [[1395.173913043478, 1568.6521739130435]], "group_id": null, "shape_type": "point", "flags": {}}, {"label": "4_pip_5", "points": [[325.60869565217376, 893.6521739130434]], "group_id": null, "shape_type": "point", "flags": {}}, {"label": "3_pip_4", "points": [[604.9565217391303, 666.4782608695651]], "group_id": null, "shape_type": "point", "flags": {}}, {"label": "2_pip_3", "points": [[894.086956521739, 574.0869565217391]], "group_id": null, "shape_type": "point", "flags": {}}, {"label": "1_pip_2", "points": [[1151.695652173913, 655.6086956521739]], "group_id": null, "shape_type": "point", "flags": {}}, {"label": "0_mcp_ip", "points": [[1502.782608695652, 1283.8695652173913]], "group_id": null, "shape_type": "point", "flags": {}}], "imagePath": "UAB130-LH.jpg", "imageData": "", "imageHeight": 2211, "imageWidth": 1695}