{"version": "4.2.4", "flags": {}, "shapes": [{"label": "w3", "points": [[657.75, 1948.25]], "group_id": null, "shape_type": "point", "flags": {}}, {"label": "w2", "points": [[904.0, 2148.25]], "group_id": null, "shape_type": "point", "flags": {}}, {"label": "w1", "points": [[1194.0, 1920.75]], "group_id": null, "shape_type": "point", "flags": {}}, {"label": "9_mcp_5", "points": [[409.0, 1357.0]], "group_id": null, "shape_type": "point", "flags": {}}, {"label": "8_mcp_4", "points": [[570.25, 1210.75]], "group_id": null, "shape_type": "point", "flags": {}}, {"label": "7_mcp_3", "points": [[785.25, 1108.25]], "group_id": null, "shape_type": "point", "flags": {}}, {"label": "6_mcp_2", "points": [[1100.25, 1099.5]], "group_id": null, "shape_type": "point", "flags": {}}, {"label": "5_mcp_1", "points": [[1477.75, 1517.0]], "group_id": null, "shape_type": "point", "flags": {}}, {"label": "4_pip_5", "points": [[305.25, 953.25]], "group_id": null, "shape_type": "point", "flags": {}}, {"label": "3_pip_4", "points": [[551.5, 715.75]], "group_id": null, "shape_type": "point", "flags": {}}, {"label": "2_pip_3", "points": [[805.25, 567.0]], "group_id": null, "shape_type": "point", "flags": {}}, {"label": "1_pip_2", "points": [[1120.25, 632.0]], "group_id": null, "shape_type": "point", "flags": {}}, {"label": "0_mcp_ip", "points": [[1614.0, 1174.5]], "group_id": null, "shape_type": "point", "flags": {}}], "imagePath": "UAB225-LH.jpg", "imageData": "", "imageHeight": 2530, "imageWidth": 1825}