{"version": "4.2.4", "flags": {}, "shapes": [{"label": "0_mcp_ip", "points": [[90.06269592476491, 376.48902821316614]], "group_id": null, "shape_type": "point", "flags": {}}, {"label": "1_pip_2", "points": [[201.97492163009406, 193.73040752351096]], "group_id": null, "shape_type": "point", "flags": {}}, {"label": "2_pip_3", "points": [[281.2852664576803, 159.8746081504702]], "group_id": null, "shape_type": "point", "flags": {}}, {"label": "3_pip_4", "points": [[370.62695924764887, 180.87774294670848]], "group_id": null, "shape_type": "point", "flags": {}}, {"label": "4_pip_5", "points": [[471.25391849529785, 251.09717868338558]], "group_id": null, "shape_type": "point", "flags": {}}, {"label": "5_mcp_1", "points": [[153.0721003134796, 438.55799373040753]], "group_id": null, "shape_type": "point", "flags": {}}, {"label": "6_mcp_2", "points": [[236.77115987460814, 311.5987460815047]], "group_id": null, "shape_type": "point", "flags": {}}, {"label": "7_mcp_3", "points": [[303.8557993730408, 296.55172413793105]], "group_id": null, "shape_type": "point", "flags": {}}, {"label": "8_mcp_4", "points": [[362.16300940438873, 314.73354231974923]], "group_id": null, "shape_type": "point", "flags": {}}, {"label": "9_mcp_5", "points": [[418.58934169278996, 341.0658307210031]], "group_id": null, "shape_type": "point", "flags": {}}, {"label": "w1", "points": [[257.7742946708464, 515.3605015673982]], "group_id": null, "shape_type": "point", "flags": {}}, {"label": "w2", "points": [[335.83072100313484, 556.4263322884012]], "group_id": null, "shape_type": "point", "flags": {}}, {"label": "w3", "points": [[396.6457680250784, 498.1191222570533]], "group_id": null, "shape_type": "point", "flags": {}}], "imagePath": "UAB335-RH.jpg", "imageData": "", "imageHeight": 638, "imageWidth": 550}