{"version": "4.2.4", "flags": {}, "shapes": [{"label": "0_mcp_ip", "points": [[253.45864661654127, 824.8195488721805]], "group_id": null, "shape_type": "point", "flags": {}}, {"label": "1_pip_2", "points": [[452.7067669172932, 476.69924812030075]], "group_id": null, "shape_type": "point", "flags": {}}, {"label": "2_pip_3", "points": [[645.9398496240601, 429.33082706766913]], "group_id": null, "shape_type": "point", "flags": {}}, {"label": "3_pip_4", "points": [[845.187969924812, 490.2330827067669]], "group_id": null, "shape_type": "point", "flags": {}}, {"label": "4_pip_5", "points": [[1008.3458646616541, 653.390977443609]], "group_id": null, "shape_type": "point", "flags": {}}, {"label": "5_mcp_1", "points": [[348.1954887218045, 1025.5714285714284]], "group_id": null, "shape_type": "point", "flags": {}}, {"label": "6_mcp_2", "points": [[530.9022556390976, 768.4285714285713]], "group_id": null, "shape_type": "point", "flags": {}}, {"label": "7_mcp_3", "points": [[680.5263157894735, 772.187969924812]], "group_id": null, "shape_type": "point", "flags": {}}, {"label": "8_mcp_4", "points": [[821.8796992481202, 815.796992481203]], "group_id": null, "shape_type": "point", "flags": {}}, {"label": "9_mcp_5", "points": [[942.9323308270675, 887.9774436090225]], "group_id": null, "shape_type": "point", "flags": {}}, {"label": "w1", "points": [[514.3609022556391, 1275.9473684210525]], "group_id": null, "shape_type": "point", "flags": {}}, {"label": "w2", "points": [[673.7593984962405, 1348.8796992481202]], "group_id": null, "shape_type": "point", "flags": {}}, {"label": "w3", "points": [[810.6015037593984, 1239.857142857143]], "group_id": null, "shape_type": "point", "flags": {}}], "imagePath": "UAB567-RH.jpg", "imageData": "", "imageHeight": 1525, "imageWidth": 1161}