{"version": "4.1.1", "flags": {}, "shapes": [{"label": "mtp_5", "points": [[290.90566037735834, 916.9811320754717]], "group_id": null, "shape_type": "point", "flags": {}}, {"label": "mtp_4", "points": [[524.8679245283017, 711.3207547169811]], "group_id": null, "shape_type": "point", "flags": {}}, {"label": "mtp_3", "points": [[707.8867924528302, 626.4150943396226]], "group_id": null, "shape_type": "point", "flags": {}}, {"label": "mtp_2", "points": [[872.0377358490566, 567.9245283018868]], "group_id": null, "shape_type": "point", "flags": {}}, {"label": "mtp_1", "points": [[1141.8490566037735, 635.8490566037735]], "group_id": null, "shape_type": "point", "flags": {}}, {"label": "mtp", "points": [[1143.7358490566037, 286.79245283018867]], "group_id": null, "shape_type": "point", "flags": {}}], "imagePath": "..\\UAB463-LF.jpg", "imageData": "", "imageHeight": 1837, "imageWidth": 1426}