{"version": "4.1.1", "flags": {}, "shapes": [{"label": "mtp_5", "points": [[259.35714285714266, 886.0714285714284]], "group_id": null, "shape_type": "point", "flags": {}}, {"label": "mtp_4", "points": [[420.07142857142844, 766.4285714285713]], "group_id": null, "shape_type": "point", "flags": {}}, {"label": "mtp_3", "points": [[570.0714285714284, 686.0714285714286]], "group_id": null, "shape_type": "point", "flags": {}}, {"label": "mtp_2", "points": [[714.7142857142856, 655.7142857142857]], "group_id": null, "shape_type": "point", "flags": {}}, {"label": "mtp_1", "points": [[989.7142857142856, 716.4285714285713]], "group_id": null, "shape_type": "point", "flags": {}}, {"label": "mtp", "points": [[912.9285714285713, 402.1428571428571]], "group_id": null, "shape_type": "point", "flags": {}}], "imagePath": "..\\UAB573-LF.jpg", "imageData": "", "imageHeight": 1728, "imageWidth": 1211}